{
  "_id": "6696c2cb763f0712c198f219",
  "name": {
    "ru": "Проверить, содержит ли массив все элементы другого массива",
    "en": "",
    "es": ""
  },
  "acceptableMistakes": 1,
  "active": true,
  "questions": [
    {
      "_id": "6696c2cb763f0712c198f21a",
      "name": {
        "ru": "Какой метод используется для добавления элемента в конец массива?",
        "en": "",
        "es": ""
      },
      "description": {
        "ru": "",
        "en": "",
        "es": ""
      },
      "answerType": "single",
      "variants": [
        {
          "_id": "6696c2cb763f0712c198f21b",
          "name": {
            "ru": "push()",
            "en": "",
            "es": ""
          },
          "correct": true
        },
        {
          "_id": "6696c2cb763f0712c198f21c",
          "name": {
            "ru": "unshift()",
            "en": "",
            "es": ""
          },
          "correct": false
        },
        {
          "_id": "6696c2cb763f0712c198f21d",
          "name": {
            "ru": "pop()",
            "en": "",
            "es": ""
          },
          "correct": false
        },
        {
          "_id": "6696c2cb763f0712c198f21e",
          "name": {
            "ru": "shift()",
            "en": "",
            "es": ""
          },
          "correct": false
        }
      ]
    },
    {
      "_id": "6696c2cb763f0712c198f21f",
      "name": {
        "ru": "Какой метод удаляет последний элемент из массива?",
        "en": "",
        "es": ""
      },
      "description": {
        "ru": "",
        "en": "",
        "es": ""
      },
      "answerType": "single",
      "variants": [
        {
          "_id": "6696c2cb763f0712c198f220",
          "name": {
            "ru": "push()",
            "en": "",
            "es": ""
          },
          "correct": false
        },
        {
          "_id": "6696c2cb763f0712c198f221",
          "name": {
            "ru": "unshift()",
            "en": "",
            "es": ""
          },
          "correct": false
        },
        {
          "_id": "6696c2cb763f0712c198f222",
          "name": {
            "ru": "pop()",
            "en": "",
            "es": ""
          },
          "correct": true
        },
        {
          "_id": "6696c2cb763f0712c198f223",
          "name": {
            "ru": "shift()",
            "en": "",
            "es": ""
          },
          "correct": false
        }
      ]
    },
    {
      "_id": "6696c2cb763f0712c198f224",
      "name": {
        "ru": "Как проверить, содержит ли массив ['apple', 'banana', 'cherry'] элемент 'banana'?",
        "en": "",
        "es": ""
      },
      "description": {
        "ru": "",
        "en": "",
        "es": ""
      },
      "answerType": "multi",
      "variants": [
        {
          "_id": "6696c2cb763f0712c198f225",
          "name": {
            "ru": "['apple', 'banana', 'cherry'].contains('banana')",
            "en": "",
            "es": ""
          },
          "correct": false
        },
        {
          "_id": "6696c2cb763f0712c198f226",
          "name": {
            "ru": "['apple', 'banana', 'cherry'].includes('banana')",
            "en": "",
            "es": ""
          },
          "correct": true
        },
        {
          "_id": "6696c2cb763f0712c198f227",
          "name": {
            "ru": "['apple', 'banana', 'cherry'].indexOf('banana') > -1",
            "en": "",
            "es": ""
          },
          "correct": true
        },
        {
          "_id": "6696c2cb763f0712c198f228",
          "name": {
            "ru": "Все ответы верны",
            "en": "",
            "es": ""
          },
          "correct": false
        }
      ]
    },
    {
      "_id": "6696c2cb763f0712c198f229",
      "name": {
        "ru": "Какой метод используется для изменения порядка элементов массива на обратный?",
        "en": "",
        "es": ""
      },
      "description": {
        "ru": "",
        "en": "",
        "es": ""
      },
      "answerType": "single",
      "variants": [
        {
          "_id": "6696c2cb763f0712c198f22a",
          "name": {
            "ru": "reverse()",
            "en": "",
            "es": ""
          },
          "correct": true
        },
        {
          "_id": "6696c2cb763f0712c198f22b",
          "name": {
            "ru": "sort()",
            "en": "",
            "es": ""
          },
          "correct": false
        },
        {
          "_id": "6696c2cb763f0712c198f22c",
          "name": {
            "ru": "flip()",
            "en": "",
            "es": ""
          },
          "correct": false
        },
        {
          "_id": "6696c2cb763f0712c198f22d",
          "name": {
            "ru": "rerange()",
            "en": "",
            "es": ""
          },
          "correct": false
        }
      ]
    },
    {
      "_id": "6696c2cb763f0712c198f22e",
      "name": {
        "ru": "Что возвращает метод arr.every(func)?",
        "en": "",
        "es": ""
      },
      "description": {
        "ru": "",
        "en": "",
        "es": ""
      },
      "answerType": "single",
      "variants": [
        {
          "_id": "6696c2cb763f0712c198f22f",
          "name": {
            "ru": "true, если функция func возвращает true для каждого элемента arr",
            "en": "",
            "es": ""
          },
          "correct": false
        },
        {
          "_id": "6696c2cb763f0712c198f230",
          "name": {
            "ru": "false, если функция func возвращает false для хотя бы одного элемента arr",
            "en": "",
            "es": ""
          },
          "correct": false
        },
        {
          "_id": "6696c2cb763f0712c198f231",
          "name": {
            "ru": "Оба вышеуказанных утверждения верны",
            "en": "",
            "es": ""
          },
          "correct": true
        },
        {
          "_id": "6696c2cb763f0712c198f232",
          "name": {
            "ru": "undefined",
            "en": "",
            "es": ""
          },
          "correct": false
        }
      ]
    },
    {
      "_id": "6696c2cb763f0712c198f233",
      "name": {
        "ru": "Какой метод массива не изменяет сам массив, а возвращает новый массив?",
        "en": "",
        "es": ""
      },
      "description": {
        "ru": "",
        "en": "",
        "es": ""
      },
      "answerType": "single",
      "variants": [
        {
          "_id": "6696c2cb763f0712c198f234",
          "name": {
            "ru": "sort()",
            "en": "",
            "es": ""
          },
          "correct": false
        },
        {
          "_id": "6696c2cb763f0712c198f235",
          "name": {
            "ru": "splice()",
            "en": "",
            "es": ""
          },
          "correct": false
        },
        {
          "_id": "6696c2cb763f0712c198f236",
          "name": {
            "ru": "slice()",
            "en": "",
            "es": ""
          },
          "correct": true
        },
        {
          "_id": "6696c2cb763f0712c198f237",
          "name": {
            "ru": "reverse()",
            "en": "",
            "es": ""
          },
          "correct": false
        }
      ]
    },
    {
      "_id": "6696c2cb763f0712c198f238",
      "name": {
        "ru": "Какое значение возвращает следующая строка?",
        "en": "",
        "es": ""
      },
      "description": {
        "ru": "```javascript\n['apple', 'banana', 'cherry'].indexOf('banana')\n```",
        "en": "",
        "es": ""
      },
      "answerType": "single",
      "variants": [
        {
          "_id": "6696c2cb763f0712c198f239",
          "name": {
            "ru": "1",
            "en": "",
            "es": ""
          },
          "correct": true
        },
        {
          "_id": "6696c2cb763f0712c198f23a",
          "name": {
            "ru": "banana",
            "en": "",
            "es": ""
          },
          "correct": false
        },
        {
          "_id": "6696c2cb763f0712c198f23b",
          "name": {
            "ru": "true",
            "en": "",
            "es": ""
          },
          "correct": false
        },
        {
          "_id": "6696c2cb763f0712c198f23c",
          "name": {
            "ru": "-1",
            "en": "",
            "es": ""
          },
          "correct": false
        }
      ]
    },
    {
      "_id": "6696c2cb763f0712c198f23d",
      "name": {
        "ru": "Какой метод нужно использовать для преобразования массива в строку, разделяя элементы запятой?",
        "en": "",
        "es": ""
      },
      "description": {
        "ru": "",
        "en": "",
        "es": ""
      },
      "answerType": "multi",
      "variants": [
        {
          "_id": "6696c2cb763f0712c198f23e",
          "name": {
            "ru": "concat(',')",
            "en": "",
            "es": ""
          },
          "correct": false
        },
        {
          "_id": "6696c2cb763f0712c198f23f",
          "name": {
            "ru": "join(',')",
            "en": "",
            "es": ""
          },
          "correct": true
        },
        {
          "_id": "6696c2cb763f0712c198f240",
          "name": {
            "ru": "toString()",
            "en": "",
            "es": ""
          },
          "correct": true
        },
        {
          "_id": "6696c2cb763f0712c198f241",
          "name": {
            "ru": "Все варианты верны",
            "en": "",
            "es": ""
          },
          "correct": false
        }
      ]
    },
    {
      "_id": "6696c2cb763f0712c198f242",
      "name": {
        "ru": "Что возвращает следующая строка?",
        "en": "",
        "es": ""
      },
      "description": {
        "ru": "```javascript\n['apple', 'banana', 'cherry'].slice(1, 2)\n```",
        "en": "",
        "es": ""
      },
      "answerType": "single",
      "variants": [
        {
          "_id": "6696c2cb763f0712c198f243",
          "name": {
            "ru": "['banana', 'cherry']",
            "en": "",
            "es": ""
          },
          "correct": false
        },
        {
          "_id": "6696c2cb763f0712c198f244",
          "name": {
            "ru": "['banana']",
            "en": "",
            "es": ""
          },
          "correct": true
        },
        {
          "_id": "6696c2cb763f0712c198f245",
          "name": {
            "ru": "['apple', 'banana']",
            "en": "",
            "es": ""
          },
          "correct": false
        },
        {
          "_id": "6696c2cb763f0712c198f246",
          "name": {
            "ru": "['apple']",
            "en": "",
            "es": ""
          },
          "correct": false
        }
      ]
    },
    {
      "_id": "6696c2cb763f0712c198f247",
      "name": {
        "ru": "Что делает следующее выражение?",
        "en": "",
        "es": ""
      },
      "description": {
        "ru": "```javascript\n['apple', 'banana', 'cherry'].join(' - ')\n```",
        "en": "",
        "es": ""
      },
      "answerType": "single",
      "variants": [
        {
          "_id": "6696c2cb763f0712c198f248",
          "name": {
            "ru": "Разделяет каждый элемент массива дефисом, возвращая новую строку",
            "en": "",
            "es": ""
          },
          "correct": true
        },
        {
          "_id": "6696c2cb763f0712c198f249",
          "name": {
            "ru": "Создает новый массив, где элементы разделены дефисами",
            "en": "",
            "es": ""
          },
          "correct": false
        },
        {
          "_id": "6696c2cb763f0712c198f24a",
          "name": {
            "ru": "Удаляет все элементы массива и заменяет их одной строкой, разделенной дефисами",
            "en": "",
            "es": ""
          },
          "correct": false
        },
        {
          "_id": "6696c2cb763f0712c198f24b",
          "name": {
            "ru": "Ничего не делает, так как метод join не существует для массивов",
            "en": "",
            "es": ""
          },
          "correct": false
        }
      ]
    }
  ]
}