{
  "_id": "6696c2cb763f0712c198f487",
  "name": {
    "ru": "Array.prototype.forEach() – выполняет функцию для каждого элемента массива",
    "en": "",
    "es": ""
  },
  "acceptableMistakes": 1,
  "active": true,
  "questions": [
    {
      "_id": "6696c2cb763f0712c198f488",
      "name": {
        "ru": "Что делает метод forEach в JavaScript?",
        "en": "",
        "es": ""
      },
      "description": {
        "ru": "",
        "en": "",
        "es": ""
      },
      "answerType": "single",
      "variants": [
        {
          "_id": "6696c2cb763f0712c198f489",
          "name": {
            "ru": "Возвращает новый массив",
            "en": "",
            "es": ""
          },
          "correct": false
        },
        {
          "_id": "6696c2cb763f0712c198f48a",
          "name": {
            "ru": "Выполняет заданную функцию один раз для каждого элемента массива",
            "en": "",
            "es": ""
          },
          "correct": true
        },
        {
          "_id": "6696c2cb763f0712c198f48b",
          "name": {
            "ru": "Изменяет оригинальный массив",
            "en": "",
            "es": ""
          },
          "correct": false
        },
        {
          "_id": "6696c2cb763f0712c198f48c",
          "name": {
            "ru": "Фильтрует элементы массива, основываясь на заданном условии",
            "en": "",
            "es": ""
          },
          "correct": false
        }
      ]
    },
    {
      "_id": "6696c2cb763f0712c198f48d",
      "name": {
        "ru": "Какие параметры принимает функция, передаваемая в метод forEach?",
        "en": "",
        "es": ""
      },
      "description": {
        "ru": "",
        "en": "",
        "es": ""
      },
      "answerType": "single",
      "variants": [
        {
          "_id": "6696c2cb763f0712c198f48e",
          "name": {
            "ru": "Только значение элемента",
            "en": "",
            "es": ""
          },
          "correct": false
        },
        {
          "_id": "6696c2cb763f0712c198f48f",
          "name": {
            "ru": "Значение элемента и его индекс",
            "en": "",
            "es": ""
          },
          "correct": false
        },
        {
          "_id": "6696c2cb763f0712c198f490",
          "name": {
            "ru": "Значение элемента, его индекс и массив",
            "en": "",
            "es": ""
          },
          "correct": true
        },
        {
          "_id": "6696c2cb763f0712c198f491",
          "name": {
            "ru": "Значение элемента и массив",
            "en": "",
            "es": ""
          },
          "correct": false
        }
      ]
    },
    {
      "_id": "6696c2cb763f0712c198f492",
      "name": {
        "ru": "Можно ли прервать выполнение метода forEach?",
        "en": "",
        "es": ""
      },
      "description": {
        "ru": "",
        "en": "",
        "es": ""
      },
      "answerType": "single",
      "variants": [
        {
          "_id": "6696c2cb763f0712c198f493",
          "name": {
            "ru": "Да, используя оператор break",
            "en": "",
            "es": ""
          },
          "correct": false
        },
        {
          "_id": "6696c2cb763f0712c198f494",
          "name": {
            "ru": "Да, используя оператор return",
            "en": "",
            "es": ""
          },
          "correct": false
        },
        {
          "_id": "6696c2cb763f0712c198f495",
          "name": {
            "ru": "Нет, forEach всегда проходит через весь массив",
            "en": "",
            "es": ""
          },
          "correct": true
        },
        {
          "_id": "6696c2cb763f0712c198f496",
          "name": {
            "ru": "Да, если функция возвращает false",
            "en": "",
            "es": ""
          },
          "correct": false
        }
      ]
    },
    {
      "_id": "6696c2cb763f0712c198f497",
      "name": {
        "ru": "Каким образом можно изменить каждый элемент массива, используя forEach?",
        "en": "",
        "es": ""
      },
      "description": {
        "ru": "",
        "en": "",
        "es": ""
      },
      "answerType": "single",
      "variants": [
        {
          "_id": "6696c2cb763f0712c198f498",
          "name": {
            "ru": "Возвращая новое значение из функции",
            "en": "",
            "es": ""
          },
          "correct": false
        },
        {
          "_id": "6696c2cb763f0712c198f499",
          "name": {
            "ru": "Напрямую изменяя элементы через их индексы",
            "en": "",
            "es": ""
          },
          "correct": true
        },
        {
          "_id": "6696c2cb763f0712c198f49a",
          "name": {
            "ru": "Используя метод map внутри forEach",
            "en": "",
            "es": ""
          },
          "correct": false
        },
        {
          "_id": "6696c2cb763f0712c198f49b",
          "name": {
            "ru": "Это невозможно сделать с помощью forEach",
            "en": "",
            "es": ""
          },
          "correct": false
        }
      ]
    },
    {
      "_id": "6696c2cb763f0712c198f49c",
      "name": {
        "ru": "Каков результат выполнения следующего кода?",
        "en": "",
        "es": ""
      },
      "description": {
        "ru": "```javascript\nlet sum = 0;\n[1, 2, 3].forEach(num => sum += num);\nconsole.log(sum);\n```",
        "en": "",
        "es": ""
      },
      "answerType": "single",
      "variants": [
        {
          "_id": "6696c2cb763f0712c198f49d",
          "name": {
            "ru": "Ошибка",
            "en": "",
            "es": ""
          },
          "correct": false
        },
        {
          "_id": "6696c2cb763f0712c198f49e",
          "name": {
            "ru": "0",
            "en": "",
            "es": ""
          },
          "correct": false
        },
        {
          "_id": "6696c2cb763f0712c198f49f",
          "name": {
            "ru": "3",
            "en": "",
            "es": ""
          },
          "correct": false
        },
        {
          "_id": "6696c2cb763f0712c198f4a0",
          "name": {
            "ru": "6",
            "en": "",
            "es": ""
          },
          "correct": true
        }
      ]
    },
    {
      "_id": "6696c2cb763f0712c198f4a1",
      "name": {
        "ru": "Что будет выведено в консоль?",
        "en": "",
        "es": ""
      },
      "description": {
        "ru": "```javascript\nconst fruits = ['Apple', 'Banana', 'Cherry'];\nfruits.forEach((fruit, index) => console.log(index));\n```",
        "en": "",
        "es": ""
      },
      "answerType": "single",
      "variants": [
        {
          "_id": "6696c2cb763f0712c198f4a2",
          "name": {
            "ru": "Apple Banana Cherry",
            "en": "",
            "es": ""
          },
          "correct": false
        },
        {
          "_id": "6696c2cb763f0712c198f4a3",
          "name": {
            "ru": "0 1 2",
            "en": "",
            "es": ""
          },
          "correct": true
        },
        {
          "_id": "6696c2cb763f0712c198f4a4",
          "name": {
            "ru": "undefined",
            "en": "",
            "es": ""
          },
          "correct": false
        },
        {
          "_id": "6696c2cb763f0712c198f4a5",
          "name": {
            "ru": "['Apple', 'Banana', 'Cherry']",
            "en": "",
            "es": ""
          },
          "correct": false
        }
      ]
    },
    {
      "_id": "6696c2cb763f0712c198f4a6",
      "name": {
        "ru": "Какова цель передачи третьего параметра в функцию обратного вызова forEach?",
        "en": "",
        "es": ""
      },
      "description": {
        "ru": "",
        "en": "",
        "es": ""
      },
      "answerType": "single",
      "variants": [
        {
          "_id": "6696c2cb763f0712c198f4a7",
          "name": {
            "ru": "Для доступа к самому массиву, который перебирается",
            "en": "",
            "es": ""
          },
          "correct": true
        },
        {
          "_id": "6696c2cb763f0712c198f4a8",
          "name": {
            "ru": "Для доступа к следующему элементу массива",
            "en": "",
            "es": ""
          },
          "correct": false
        },
        {
          "_id": "6696c2cb763f0712c198f4a9",
          "name": {
            "ru": "Для изменения оригинального массива",
            "en": "",
            "es": ""
          },
          "correct": false
        },
        {
          "_id": "6696c2cb763f0712c198f4aa",
          "name": {
            "ru": "Это не имеет никакого эффекта",
            "en": "",
            "es": ""
          },
          "correct": false
        }
      ]
    },
    {
      "_id": "6696c2cb763f0712c198f4ab",
      "name": {
        "ru": "Может ли метод forEach работать с объектами, а не только с массивами?",
        "en": "",
        "es": ""
      },
      "description": {
        "ru": "",
        "en": "",
        "es": ""
      },
      "answerType": "single",
      "variants": [
        {
          "_id": "6696c2cb763f0712c198f4ac",
          "name": {
            "ru": "Да, с любыми объектами.",
            "en": "",
            "es": ""
          },
          "correct": false
        },
        {
          "_id": "6696c2cb763f0712c198f4ad",
          "name": {
            "ru": "Нет, только с массивоподобными объектами.",
            "en": "",
            "es": ""
          },
          "correct": false
        },
        {
          "_id": "6696c2cb763f0712c198f4ae",
          "name": {
            "ru": "Да, если использовать Object.keys() или Object.entries().",
            "en": "",
            "es": ""
          },
          "correct": true
        },
        {
          "_id": "6696c2cb763f0712c198f4af",
          "name": {
            "ru": "Нет, forEach исключительно для массивов.",
            "en": "",
            "es": ""
          },
          "correct": false
        }
      ]
    },
    {
      "_id": "6696c2cb763f0712c198f4b0",
      "name": {
        "ru": "Как правильно вызвать forEach на массиве numbers?",
        "en": "",
        "es": ""
      },
      "description": {
        "ru": "",
        "en": "",
        "es": ""
      },
      "answerType": "single",
      "variants": [
        {
          "_id": "6696c2cb763f0712c198f4b1",
          "name": {
            "ru": "```javascript\nforEach(numbers => console.log(numbers));\n```",
            "en": "",
            "es": ""
          },
          "correct": false
        },
        {
          "_id": "6696c2cb763f0712c198f4b2",
          "name": {
            "ru": "```javascript\nnumbers.forEach(number => console.log(number));\n```",
            "en": "",
            "es": ""
          },
          "correct": true
        },
        {
          "_id": "6696c2cb763f0712c198f4b3",
          "name": {
            "ru": "```javascript\nnumbers.forEach(console.log(number));\n```",
            "en": "",
            "es": ""
          },
          "correct": false
        },
        {
          "_id": "6696c2cb763f0712c198f4b4",
          "name": {
            "ru": "```javascript\nforEach(numbers, number => console.log(number));\n```",
            "en": "",
            "es": ""
          },
          "correct": false
        }
      ]
    },
    {
      "_id": "6696c2cb763f0712c198f4b5",
      "name": {
        "ru": "Что будет результатом выполнения следующего кода?",
        "en": "",
        "es": ""
      },
      "description": {
        "ru": "```javascript\nconst letters = ['a', 'b', 'c', 'd'];\nletters.forEach((letter, index, arr) => arr[index] = letter.toUpperCase());\nconsole.log(letters);\n```",
        "en": "",
        "es": ""
      },
      "answerType": "single",
      "variants": [
        {
          "_id": "6696c2cb763f0712c198f4b6",
          "name": {
            "ru": "['a', 'b', 'c', 'd']",
            "en": "",
            "es": ""
          },
          "correct": false
        },
        {
          "_id": "6696c2cb763f0712c198f4b7",
          "name": {
            "ru": "['A', 'B', 'C', 'D']",
            "en": "",
            "es": ""
          },
          "correct": true
        },
        {
          "_id": "6696c2cb763f0712c198f4b8",
          "name": {
            "ru": "undefined",
            "en": "",
            "es": ""
          },
          "correct": false
        },
        {
          "_id": "6696c2cb763f0712c198f4b9",
          "name": {
            "ru": "[0, 1, 2, 3]",
            "en": "",
            "es": ""
          },
          "correct": false
        }
      ]
    }
  ]
}